secure_hardware_extension/__init__.py
secure_hardware_extension/constants.py
secure_hardware_extension/datatypes.py
secure_hardware_extension/memory_update.py
secure_hardware_extension/key_slots/__init__.py
secure_hardware_extension/key_slots/autosar.py
secure_hardware_extension/key_slots/base.py
securehardwareextension-1.0.1.dist-info/licenses/LICENSE
securehardwareextension-1.0.1.dist-info/METADATA
securehardwareextension-1.0.1.dist-info/WHEEL
securehardwareextension-1.0.1.dist-info/top_level.txt
securehardwareextension-1.0.1.dist-info/RECORD
